autodistill_florence_2/__init__.py
autodistill_florence_2/model.py
autodistill_florence_2-0.1.1.dist-info/METADATA
autodistill_florence_2-0.1.1.dist-info/WHEEL
autodistill_florence_2-0.1.1.dist-info/top_level.txt
autodistill_florence_2-0.1.1.dist-info/RECORD
