Metadata-Version: 2.1
Name: autodistill-florence-2
Version: 0.1.1
Summary: Use Florence 2 to auto-label data for use in training fine-tuned object detection models. 
Home-page: https://github.com/autodistill/autodistill-florence-2
Author: Roboflow
Author-email: support@roboflow.com
Classifier: Programming Language :: Python :: 3
Classifier: License :: OSI Approved :: MIT License
Classifier: Operating System :: OS Independent
Requires-Python: >=3.7
Requires-Dist: transformers
Requires-Dist: einops
Requires-Dist: flash-attn
Requires-Dist: timm
Requires-Dist: numpy
Requires-Dist: supervision
Requires-Dist: roboflow
Requires-Dist: peft
Requires-Dist: Pillow
Requires-Dist: tqdm
Requires-Dist: autodistill
Provides-Extra: dev
Requires-Dist: flake8 ; extra == 'dev'
Requires-Dist: black ==22.3.0 ; extra == 'dev'
Requires-Dist: isort ; extra == 'dev'
Requires-Dist: twine ; extra == 'dev'
Requires-Dist: pytest ; extra == 'dev'
Requires-Dist: wheel ; extra == 'dev'
